gblmf_distributions/Binomialdistribution.py
gblmf_distributions/Gaussiandistribution.py
gblmf_distributions/Generaldistribution.py
gblmf_distributions/__init__.py
gblmf_distributions-0.1.dist-info/DESCRIPTION.rst
gblmf_distributions-0.1.dist-info/METADATA
gblmf_distributions-0.1.dist-info/RECORD
gblmf_distributions-0.1.dist-info/WHEEL
gblmf_distributions-0.1.dist-info/metadata.json
gblmf_distributions-0.1.dist-info/top_level.txt
