Metadata-Version: 2.0
Name: gblmf-distributions
Version: 0.1
Summary: Gaussian and Binomial distributions
Home-page: UNKNOWN
Author: Luis Ferreira
Author-email: luismatosferreira@gmail.com
License: UNKNOWN
Platform: UNKNOWN
